MessageFactory/Util.py
MessageFactory/__init__.py
ProtobufMessageFactory-0.1.3.dist-info/LICENSE
ProtobufMessageFactory-0.1.3.dist-info/METADATA
ProtobufMessageFactory-0.1.3.dist-info/WHEEL
ProtobufMessageFactory-0.1.3.dist-info/top_level.txt
ProtobufMessageFactory-0.1.3.dist-info/RECORD
