Metadata-Version: 2.1
Name: ProtobufMessageFactory
Version: 0.1.3
Summary: This package tries to ease up the work with protobuf messages in python.
Home-page: https://github.com/cimera255/ProtobufMessageFactory
Author: cimera255
Author-email: author@example.com
License: UNKNOWN
Platform: UNKNOWN
Classifier: Programming Language :: Python :: 3
Classifier: License :: OSI Approved :: MIT License
Classifier: Operating System :: OS Independent
Requires-Python: >=3.6
Requires-Dist: protobuf
